basepackage/__init__.py
basepackage/module.py
basepackage-0.1.1.dist-info/LICENCE.txt
basepackage-0.1.1.dist-info/METADATA
basepackage-0.1.1.dist-info/WHEEL
basepackage-0.1.1.dist-info/top_level.txt
basepackage-0.1.1.dist-info/RECORD
