Metadata-Version: 2.1
Name: basepackage
Version: 0.1.1
Summary: This package includes some, for me, helpful small things.
Home-page: https://github.com/users/LuciferMonao/projects/2
Author: Lucifer Monao
Author-email: Lucifermonao@gmx.de
License: UNKNOWN
Platform: UNKNOWN
Classifier: Programming Language :: Python :: 3
Classifier: License :: OSI Approved :: MIT License
Classifier: Operating System :: OS Independent
Requires-Python: >=3.6
